Metadata-Version: 1.1
Name: SimpleMinecraftAPI
Version: 1.0
Summary: SimpleMinecraftAPI that return skin,body,head,cape,id
Home-page: UNKNOWN
Author: Zaid Ali
Author-email: realarty69@gmail.com
License: MIT
Keywords: minecraft,api
Platform: UNKNOWN
Classifier: Development Status :: 1 - Planning
Classifier: Intended Audience :: Developers
Classifier: Programming Language :: Python :: 3
Classifier: Operating System :: Unix
Classifier: Operating System :: MacOS :: MacOS X
Classifier: Operating System :: Microsoft :: Windows
